{"chunk_definitions":[{"row":20,"row_count":1,"visible":true,"expansion_state":0,"options":{"engine":"r","label":"unnamed-chunk-22","dev":"png"},"document_id":"45CB59F2","chunk_id":"cmi852cogskyn","chunk_label":"unnamed-chunk-1"},{"row":118,"row_count":1,"visible":true,"expansion_state":0,"options":{"engine":"R","label":"unnamed-chunk-23","dev":"png"},"document_id":"E23C40BB","chunk_id":"cde8cw7gv5r9q","chunk_label":"unnamed-chunk-2"},{"row":162,"row_count":1,"visible":true,"expansion_state":0,"options":{"engine":"r","label":"unnamed-chunk-41","dev":"png"},"document_id":"E23C40BB","chunk_id":"calefoxgix88v","chunk_label":"unnamed-chunk-3"},{"row":216,"row_count":1,"visible":true,"expansion_state":0,"options":{"engine":"R","label":"unnamed-chunk-21","dev":"png"},"document_id":"E23C40BB","chunk_id":"cs5w380jt32oe","chunk_label":"unnamed-chunk-4"}],"doc_write_time":1728676090}